LICENSE
MANIFEST.in
README
colors.py
setup.cfg
setup.py
doc/Makefile
doc/conf.py
doc/index.rst
doc/_build/.keep
doc/_static/.keep
doc/_templates/.keep
pycolors.egg-info/PKG-INFO
pycolors.egg-info/SOURCES.txt
pycolors.egg-info/dependency_links.txt
pycolors.egg-info/top_level.txt