Metadata-Version: 1.0
Name: pycolors
Version: 0.1.2
Summary: Python module to ease the use of colors on programs that run on CLI
Home-page: http://packages.python.org/pycolors/
Author: Rafael Goncalves Martins
Author-email: rafael@rafaelmartins.eng.br
License: BSD
Platform: any
Classifier: Programming Language :: Python
Classifier: Intended Audience :: Developers
Classifier: Operating System :: OS Independent
Classifier: License :: OSI Approved :: BSD License
Classifier: Topic :: Software Development :: Libraries :: Python Modules
